zotero/VERSION.txt
zotero/__info__.py
zotero/__init__.py
zotero/__main__.py
zotero/gpt.py
zotero_cli_tool-1.7.4.dist-info/licenses/LICENSE
zotero_cli_tool-1.7.4.dist-info/METADATA
zotero_cli_tool-1.7.4.dist-info/WHEEL
zotero_cli_tool-1.7.4.dist-info/entry_points.txt
zotero_cli_tool-1.7.4.dist-info/top_level.txt
zotero_cli_tool-1.7.4.dist-info/RECORD
