Metadata-Version: 2.4
Name: zotero-cli-tool
Version: 1.7.4
Summary: Tinyscript tool for sorting and exporting Zotero references based on pyzotero
Author-email: Alexandre D'Hondt <alexandre.dhondt@gmail.com>
License-Expression: GPL-3.0-or-later
Project-URL: homepage, https://github.com/dhondta/zotero-cli
Project-URL: issues, https://github.com/dhondta/zotero-cli/issues
Project-URL: repository, https://github.com/dhondta/zotero-cli
Keywords: zotero,citations,cli-app,tinyscript
Classifier: Development Status :: 5 - Production/Stable
Classifier: Environment :: Console
Classifier: Intended Audience :: Science/Research
Classifier: Programming Language :: Python :: 3
Requires-Python: <4,>=3.8
License-File: LICENSE
Requires-Dist: fonttools>=4.43.0
Requires-Dist: matplotlib
Requires-Dist: pyzotero
Requires-Dist: tinyscript>=1.30.22
Requires-Dist: xlsxwriter
Provides-Extra: gpt
Requires-Dist: chromadb; extra == "gpt"
Requires-Dist: crypt-r; sys_platform != "darwin" and extra == "gpt"
Requires-Dist: fastapi>=0.109.1; extra == "gpt"
Requires-Dist: gpt4all; extra == "gpt"
Requires-Dist: langchain>=0.0.225; extra == "gpt"
Requires-Dist: llama-cpp-python; extra == "gpt"
Requires-Dist: numpy>=1.22.2; extra == "gpt"
Requires-Dist: requests>=2.32.2; extra == "gpt"
Requires-Dist: sympy>=1.12; extra == "gpt"
Requires-Dist: tqdm; extra == "gpt"
Dynamic: license-file
